ghmap/__init__.py
ghmap/cli.py
ghmap/utils.py
ghmap/config/action_to_activity.json
ghmap/config/event_to_action.json
ghmap/mapping/__init__.py
ghmap/mapping/action_mapper.py
ghmap/mapping/activity_mapper.py
ghmap/preprocess/__init__.py
ghmap/preprocess/event_processor.py
ghmap-1.0.6.dist-info/licenses/LICENSE
ghmap-1.0.6.dist-info/METADATA
ghmap-1.0.6.dist-info/WHEEL
ghmap-1.0.6.dist-info/entry_points.txt
ghmap-1.0.6.dist-info/top_level.txt
ghmap-1.0.6.dist-info/RECORD
