Metadata-Version: 2.4
Name: ghmap
Version: 1.0.6
Summary: GitHub event mapping tool
Author-email: Youness Hourri <youness.hourri@umons.ac.be>
License: MIT License
Project-URL: Homepage, https://github.com/uhourri/ghmap
Classifier: Programming Language :: Python :: 3
Classifier: License :: OSI Approved :: MIT License
Classifier: Operating System :: OS Independent
Classifier: Intended Audience :: Science/Research
Classifier: Topic :: Scientific/Engineering
Classifier: Programming Language :: Python :: 3 :: Only
Classifier: Programming Language :: Python :: 3.10
Classifier: Programming Language :: Python :: 3.11
Classifier: Programming Language :: Python :: 3.12
Classifier: Programming Language :: Python :: 3.13
Requires-Python: >=3.10
License-File: LICENSE
Requires-Dist: tqdm==4.67.1
Requires-Dist: pytest==8.4.2
Dynamic: license-file
